django_oscar_worldpay-1.3.dist-info/DESCRIPTION.rst
django_oscar_worldpay-1.3.dist-info/METADATA
django_oscar_worldpay-1.3.dist-info/RECORD
django_oscar_worldpay-1.3.dist-info/WHEEL
django_oscar_worldpay-1.3.dist-info/metadata.json
django_oscar_worldpay-1.3.dist-info/top_level.txt
worldpay/__init__.py
worldpay/admin.py
worldpay/base.py
worldpay/exceptions.py
worldpay/facade.py
worldpay/gateway.py
worldpay/models.py
worldpay/urls.py
worldpay/views.py
worldpay/templates/worldpay/preview.html
worldpay/templates/worldpay/worldpay_response.html
