Metadata-Version: 2.0
Name: django-oscar-worldpay
Version: 1.3
Summary: Integration with Worldpay payments for django-oscar
Home-page: https://github.com/matthewwilkes/django-oscar-worldpay
Author: Matthew Wilkes
Author-email: django-oscar-worldpay@matthewwilkes.name
License: Copyright (c) 2011-2015, Matthew Wilkes, Tangent Communications PLC and individual contributors.
Requires-Dist: django-localflavor
Requires-Dist: requests (>=1.0)
Requires-Dist: six
Provides-Extra: oscar
Requires-Dist: django-oscar (>=0.6); extra == 'oscar'
